[
  {
    "y": 576,
    "x": 1622,
    "z": 7
  },
  {
    "y": 576,
    "x": 1615,
    "z": 7
  },
  {
    "y": 577,
    "x": 1604,
    "z": 7
  },
  {
    "y": 581,
    "x": 1596,
    "z": 7
  },
  {
    "y": 578,
    "x": 1589,
    "z": 7
  },
  {
    "y": 583,
    "x": 1583,
    "z": 7
  },
  {
    "y": 580,
    "x": 1578,
    "z": 7
  },
  {
    "y": 581,
    "x": 1565,
    "z": 7
  },
  {
    "y": 576,
    "x": 1552,
    "z": 7
  },
  {
    "y": 575,
    "x": 1564,
    "z": 7
  },
  {
    "y": 572,
    "x": 1572,
    "z": 7
  },
  {
    "y": 574,
    "x": 1583,
    "z": 7
  },
  {
    "y": 578,
    "x": 1591,
    "z": 7
  },
  {
    "y": 574,
    "x": 1592,
    "z": 7
  },
  {
    "y": 573,
    "x": 1596,
    "z": 7
  },
  {
    "y": 575,
    "x": 1601,
    "z": 7
  },
  {
    "y": 576,
    "x": 1611,
    "z": 7
  },
  {
    "y": 577,
    "x": 1624,
    "z": 7
  },
  {
    "y": 578,
    "x": 1631,
    "z": 7
  },
  {
    "y": 578,
    "x": 1641,
    "z": 7
  },
  {
    "y": 577,
    "x": 1648,
    "z": 7
  },
  {
    "y": 576,
    "x": 1652,
    "z": 7
  },
  {
    "y": 576,
    "x": 1662,
    "z": 7
  },
  {
    "y": 576,
    "x": 1668,
    "z": 7
  },
  {
    "y": 575,
    "x": 1657,
    "z": 7
  },
  {
    "y": 575,
    "x": 1648,
    "z": 7
  },
  {
    "y": 575,
    "x": 1636,
    "z": 7
  },
  {
    "y": 569,
    "x": 1631,
    "z": 7
  },
  {
    "y": 560,
    "x": 1631,
    "z": 7
  },
  {
    "y": 553,
    "x": 1631,
    "z": 7
  },
  {
    "y": 544,
    "x": 1631,
    "z": 7
  },
  {
    "y": 540,
    "x": 1627,
    "z": 7
  },
  {
    "y": 545,
    "x": 1626,
    "z": 7
  },
  {
    "y": 553,
    "x": 1626,
    "z": 7
  },
  {
    "y": 561,
    "x": 1626,
    "z": 7
  },
  {
    "y": 565,
    "x": 1625,
    "z": 7
  },
  {
    "y": 570,
    "x": 1625,
    "z": 7
  }
]